<data>
	<entity Group="Bosses" ID="630" Image="icons/AH/famine2.png" Kind="Alt Horsemen" Name="Tainted Famine" Subtype="0" Variant="101" />
	<entity Group="Bosses" ID="650" Image="icons/AH/war2.png" Kind="Alt Horsemen" Name="Tainted War" Subtype="0" Variant="101" />
	<entity Group="Bosses" ID="660" Image="icons/AH/death2.png" Kind="Alt Horsemen" Name="Tainted Death" Subtype="0" Variant="101" />
	<entity Group="Bosses" ID="660" Image="icons/AH/death2.png" Kind="Alt Horsemen" Name="Tainted Death (tp safe)" Subtype="1" Variant="101" />
	<entity Group="Bosses" ID="640" Image="icons/AH/pestilence2.png" Kind="Alt Horsemen" Name="Tainted Pestilence" Subtype="0" Variant="101" />
	
    <entity Group="Monsters" ID="651" Image="icons/AH/army.png" Kind="Alt Horsemen" Name="Army (Random)" Subtype="0" Variant="101" />
	<entity Group="Monsters" ID="651" Image="icons/AH/army2.png" Kind="Alt Horsemen" Name="Army (No Modifiers)" Subtype="10" Variant="101" />
	<entity Group="Monsters" ID="651" Image="icons/AH/army3.png" Kind="Alt Horsemen" Name="Army (Helmet)" Subtype="3" Variant="101" />
	<entity Group="Monsters" ID="651" Image="icons/AH/army4.png" Kind="Alt Horsemen" Name="Army (Bomb)" Subtype="4" Variant="101" />
	
	<entity Group="Monsters" ID="651" Image="icons/AH/army5.png" Kind="Alt Horsemen" Name="Army Bomb Thrower (Random)" Subtype="0" Variant="102" />
</data>
